chunkcrypt/__init__.py
chunkcrypt/cryptchunk.py
chunkcrypt-0.0.3.dist-info/LICENSE
chunkcrypt-0.0.3.dist-info/METADATA
chunkcrypt-0.0.3.dist-info/WHEEL
chunkcrypt-0.0.3.dist-info/top_level.txt
chunkcrypt-0.0.3.dist-info/RECORD
