Metadata-Version: 2.1
Name: chunkcrypt
Version: 0.0.3
Summary: Simple encryption and decryption by chunk
Home-page: https://github.com/paulo-lucero/chunkcrypt
Author: Paulo
Author-email: paulolucero00@gmail.com
Classifier: Programming Language :: Python :: 3
Classifier: License :: OSI Approved :: MIT License
Classifier: Operating System :: OS Independent
Classifier: Development Status :: 7 - Inactive
Requires-Python: >=3.9
License-File: LICENSE
Requires-Dist: cryptography
Requires-Dist: requests
